{
	"info": {
		"_postman_id": "20021154-ce28-46c0-8d72-34771bb3c02b",
		"name": "DeploymentStrategies",
		"schema": "https://schema.getpostman.com/json/collection/v2.1.0/collection.json"
	},
	"item": [
		{
			"name": "DeploymentStrategies",
			"event": [
				{
					"listen": "test",
					"script": {
						"id": "5154446d-1ad7-4d3a-a8b5-99ff3721b974",
						"exec": [
							"pm.test(\"Is Blue\", function () {\r",
							"    pm.expect(pm.response.text()).to.include(\"healthy\");\r",
							"});"
						],
						"type": "text/javascript"
					}
				}
			],
			"protocolProfileBehavior": {
				"disableBodyPruning": true
			},
			"request": {
				"auth": {
					"type": "noauth"
				},
				"method": "GET",
				"header": [
					{
						"key": "Host",
						"value": "superapp.default.svc.cluster.local",
						"type": "text"
					}
				],
				"body": {
					"mode": "raw",
					"raw": ""
				},
				"url": {
					"raw": "http://{{ingress_ip}}/version",
					"protocol": "http",
					"host": [
						"{{ingress_ip}}"
					],
					"path": [
						"version"
					]
				}
			},
			"response": []
		},
		{
			"name": "DeploymentStrategies2",
			"event": [
				{
					"listen": "test",
					"script": {
						"id": "5154446d-1ad7-4d3a-a8b5-99ff3721b974",
						"exec": [
							"pm.test(\"Is Blue\", function () {\r",
							"    pm.expect(pm.response.text()).to.include(\"healthy\");\r",
							"});"
						],
						"type": "text/javascript"
					}
				}
			],
			"protocolProfileBehavior": {
				"disableBodyPruning": true
			},
			"request": {
				"auth": {
					"type": "noauth"
				},
				"method": "GET",
				"header": [
					{
						"key": "Host",
						"value": "superapp.default.svc.cluster.local",
						"type": "text"
					}
				],
				"body": {
					"mode": "raw",
					"raw": ""
				},
				"url": {
					"raw": "http://{{ingress_ip}}/version",
					"protocol": "http",
					"host": [
						"{{ingress_ip}}"
					],
					"path": [
						"version"
					]
				}
			},
			"response": []
		},
		{
			"name": "DeploymentStrategies3",
			"event": [
				{
					"listen": "test",
					"script": {
						"id": "5154446d-1ad7-4d3a-a8b5-99ff3721b974",
						"exec": [
							"pm.test(\"Is Blue\", function () {\r",
							"    pm.expect(pm.response.text()).to.include(\"healthy\");\r",
							"});"
						],
						"type": "text/javascript"
					}
				}
			],
			"protocolProfileBehavior": {
				"disableBodyPruning": true
			},
			"request": {
				"auth": {
					"type": "noauth"
				},
				"method": "GET",
				"header": [
					{
						"key": "Host",
						"value": "superapp.default.svc.cluster.local",
						"type": "text"
					}
				],
				"body": {
					"mode": "raw",
					"raw": ""
				},
				"url": {
					"raw": "http://{{ingress_ip}}/version",
					"protocol": "http",
					"host": [
						"{{ingress_ip}}"
					],
					"path": [
						"version"
					]
				}
			},
			"response": []
		},
		{
			"name": "DeploymentStrategies4",
			"event": [
				{
					"listen": "test",
					"script": {
						"id": "5154446d-1ad7-4d3a-a8b5-99ff3721b974",
						"exec": [
							"pm.test(\"Is Blue\", function () {\r",
							"    pm.expect(pm.response.text()).to.include(\"healthy\");\r",
							"});"
						],
						"type": "text/javascript"
					}
				}
			],
			"protocolProfileBehavior": {
				"disableBodyPruning": true
			},
			"request": {
				"auth": {
					"type": "noauth"
				},
				"method": "GET",
				"header": [
					{
						"key": "Host",
						"value": "superapp.default.svc.cluster.local",
						"type": "text"
					}
				],
				"body": {
					"mode": "raw",
					"raw": ""
				},
				"url": {
					"raw": "http://{{ingress_ip}}/version",
					"protocol": "http",
					"host": [
						"{{ingress_ip}}"
					],
					"path": [
						"version"
					]
				}
			},
			"response": []
		},
		{
			"name": "DeploymentStrategies5",
			"event": [
				{
					"listen": "test",
					"script": {
						"id": "5154446d-1ad7-4d3a-a8b5-99ff3721b974",
						"exec": [
							"pm.test(\"Is Blue\", function () {\r",
							"    pm.expect(pm.response.text()).to.include(\"healthy\");\r",
							"});"
						],
						"type": "text/javascript"
					}
				}
			],
			"protocolProfileBehavior": {
				"disableBodyPruning": true
			},
			"request": {
				"auth": {
					"type": "noauth"
				},
				"method": "GET",
				"header": [
					{
						"key": "Host",
						"value": "superapp.default.svc.cluster.local",
						"type": "text"
					}
				],
				"body": {
					"mode": "raw",
					"raw": ""
				},
				"url": {
					"raw": "http://{{ingress_ip}}/version",
					"protocol": "http",
					"host": [
						"{{ingress_ip}}"
					],
					"path": [
						"version"
					]
				}
			},
			"response": []
		},
		{
			"name": "DeploymentStrategies6",
			"event": [
				{
					"listen": "test",
					"script": {
						"id": "5154446d-1ad7-4d3a-a8b5-99ff3721b974",
						"exec": [
							"pm.test(\"Is Blue\", function () {\r",
							"    pm.expect(pm.response.text()).to.include(\"healthy\");\r",
							"});"
						],
						"type": "text/javascript"
					}
				}
			],
			"protocolProfileBehavior": {
				"disableBodyPruning": true
			},
			"request": {
				"auth": {
					"type": "noauth"
				},
				"method": "GET",
				"header": [
					{
						"key": "Host",
						"value": "superapp.default.svc.cluster.local",
						"type": "text"
					}
				],
				"body": {
					"mode": "raw",
					"raw": ""
				},
				"url": {
					"raw": "http://{{ingress_ip}}/version",
					"protocol": "http",
					"host": [
						"{{ingress_ip}}"
					],
					"path": [
						"version"
					]
				}
			},
			"response": []
		},
		{
			"name": "DeploymentStrategies7",
			"event": [
				{
					"listen": "test",
					"script": {
						"id": "5154446d-1ad7-4d3a-a8b5-99ff3721b974",
						"exec": [
							"pm.test(\"Is Blue\", function () {\r",
							"    pm.expect(pm.response.text()).to.include(\"healthy\");\r",
							"});"
						],
						"type": "text/javascript"
					}
				}
			],
			"protocolProfileBehavior": {
				"disableBodyPruning": true
			},
			"request": {
				"auth": {
					"type": "noauth"
				},
				"method": "GET",
				"header": [
					{
						"key": "Host",
						"value": "superapp.default.svc.cluster.local",
						"type": "text"
					}
				],
				"body": {
					"mode": "raw",
					"raw": ""
				},
				"url": {
					"raw": "http://{{ingress_ip}}/version",
					"protocol": "http",
					"host": [
						"{{ingress_ip}}"
					],
					"path": [
						"version"
					]
				}
			},
			"response": []
		},
		{
			"name": "DeploymentStrategies8",
			"event": [
				{
					"listen": "test",
					"script": {
						"id": "5154446d-1ad7-4d3a-a8b5-99ff3721b974",
						"exec": [
							"pm.test(\"Is Blue\", function () {\r",
							"    pm.expect(pm.response.text()).to.include(\"healthy\");\r",
							"});"
						],
						"type": "text/javascript"
					}
				}
			],
			"protocolProfileBehavior": {
				"disableBodyPruning": true
			},
			"request": {
				"auth": {
					"type": "noauth"
				},
				"method": "GET",
				"header": [
					{
						"key": "Host",
						"value": "superapp.default.svc.cluster.local",
						"type": "text"
					}
				],
				"body": {
					"mode": "raw",
					"raw": ""
				},
				"url": {
					"raw": "http://{{ingress_ip}}/version",
					"protocol": "http",
					"host": [
						"{{ingress_ip}}"
					],
					"path": [
						"version"
					]
				}
			},
			"response": []
		},
		{
			"name": "DeploymentStrategies9",
			"event": [
				{
					"listen": "test",
					"script": {
						"id": "5154446d-1ad7-4d3a-a8b5-99ff3721b974",
						"exec": [
							"pm.test(\"Is Blue\", function () {\r",
							"    pm.expect(pm.response.text()).to.include(\"healthy\");\r",
							"});"
						],
						"type": "text/javascript"
					}
				}
			],
			"protocolProfileBehavior": {
				"disableBodyPruning": true
			},
			"request": {
				"auth": {
					"type": "noauth"
				},
				"method": "GET",
				"header": [
					{
						"key": "Host",
						"value": "superapp.default.svc.cluster.local",
						"type": "text"
					}
				],
				"body": {
					"mode": "raw",
					"raw": ""
				},
				"url": {
					"raw": "http://{{ingress_ip}}/version",
					"protocol": "http",
					"host": [
						"{{ingress_ip}}"
					],
					"path": [
						"version"
					]
				}
			},
			"response": []
		},
		{
			"name": "DeploymentStrategies10",
			"event": [
				{
					"listen": "test",
					"script": {
						"id": "5154446d-1ad7-4d3a-a8b5-99ff3721b974",
						"exec": [
							"pm.test(\"Is Blue\", function () {\r",
							"    pm.expect(pm.response.text()).to.include(\"healthy\");\r",
							"});"
						],
						"type": "text/javascript"
					}
				}
			],
			"protocolProfileBehavior": {
				"disableBodyPruning": true
			},
			"request": {
				"auth": {
					"type": "noauth"
				},
				"method": "GET",
				"header": [
					{
						"key": "Host",
						"value": "superapp.default.svc.cluster.local",
						"type": "text"
					}
				],
				"body": {
					"mode": "raw",
					"raw": ""
				},
				"url": {
					"raw": "http://{{ingress_ip}}/version",
					"protocol": "http",
					"host": [
						"{{ingress_ip}}"
					],
					"path": [
						"version"
					]
				}
			},
			"response": []
		}
	],
	"event": [
		{
			"listen": "prerequest",
			"script": {
				"id": "07db8698-07a8-456e-bef2-4c4762e5cac5",
				"type": "text/javascript",
				"exec": [
					""
				]
			}
		},
		{
			"listen": "test",
			"script": {
				"id": "f80cb59c-785e-4e68-8552-b16afe482de0",
				"type": "text/javascript",
				"exec": [
					""
				]
			}
		}
	],
	"variable": [
		{
			"id": "7ae53d03-5840-41ea-9d88-e77cd5c5fcf7",
			"key": "ingress_ip",
			"value": "INGRESS_IP",
			"type": "string"
		}
	],
	"protocolProfileBehavior": {}
}